cdispyutils/__init__.py
cdispyutils/auth/__init__.py
cdispyutils/auth/errors.py
cdispyutils/auth/jwt_validation.py
cdispyutils/config/__init__.py
cdispyutils/constants.py
cdispyutils/hmac4/__init__.py
cdispyutils/hmac4/error.py
cdispyutils/hmac4/hmac4_auth.py
cdispyutils/hmac4/hmac4_auth_generator.py
cdispyutils/hmac4/hmac4_auth_parser.py
cdispyutils/hmac4/hmac4_auth_validator.py
cdispyutils/hmac4/hmac4_signing_key.py
cdispyutils/log.py
cdispyutils/metrics.py
cdispyutils/profiling/README.md
cdispyutils/profiling/__init__.py
cdispyutils/profiling/images/profile_graph_example.png
cdispyutils/profiling/profiler.py
cdispyutils/profiling/vis.py
cdispyutils/uwsgi.py
cdispyutils-2.5.0.dist-info/METADATA
cdispyutils-2.5.0.dist-info/WHEEL
cdispyutils-2.5.0.dist-info/licenses/LICENSE
cdispyutils-2.5.0.dist-info/licenses/NOTICE
cdispyutils-2.5.0.dist-info/RECORD
